{
    "projects": [
        {
            "id": "0",
            "imgUrl": "img/android-decal.jpg",
            "imgAlt": "SEPTA Android App",
            "name": "SEPTA Android App",
            "url": "https://play.google.com/store/apps/details?id=org.septa.android.app",
            "desc": "The official SEPTA app brings our entire transit network directly to you with convenient access to schedule information, real-time updates, trip planning, fare options, social media connections, and Customer Service. This new app is perfect for customers on the go with your best SEPTA travel options right at your fingertips.",
            "tags": "Android, Open Source, SEPTA"
        },
		{
			"id": "1",
			"imgUrl": "img/SEPTA.jpg",
			"imgAlt": "SEPTA iOS App",
			"name": "SEPTA iOS App",
			"url": "https://itunes.apple.com/us/app/septa/id724915219?mt=8",
			"desc": "The official SEPTA app brings our entire transit network directly to you with convenient access to schedule information, real-time updates, trip planning, fare options, social media connections, and Customer Service. This new app is perfect for customers on the go with your best SEPTA travel options right at your fingertips.",
			"tags": "iOS, SEPTA" 
		}
    ]
}
